leequotes/__init__.py
leequotes/leequotes.py
leequotes/data/__init__.py
leequotes/data/quotes.tsv
leequotes-0.0.9.dist-info/LICENSE
leequotes-0.0.9.dist-info/METADATA
leequotes-0.0.9.dist-info/WHEEL
leequotes-0.0.9.dist-info/entry_points.txt
leequotes-0.0.9.dist-info/top_level.txt
leequotes-0.0.9.dist-info/RECORD
