Metadata-Version: 2.1
Name: leequotes
Version: 0.0.9
Summary: A python package that provides Bruce Lee quotes
Author-email: Alexandre Petit <lxnd@proton.me>
License: MIT License
Project-URL: Repository, https://github.com/lxnd-dune/leequotes
Keywords: Bruce,Lee,quotes,wisdom
Classifier: Programming Language :: Python :: 3
License-File: LICENSE
